python_hatch_template_win/__about__.py
python_hatch_template_win/__init__.py
python_hatch_template_win-0.0.1.dist-info/METADATA
python_hatch_template_win-0.0.1.dist-info/WHEEL
python_hatch_template_win-0.0.1.dist-info/licenses/LICENSE.txt
python_hatch_template_win-0.0.1.dist-info/RECORD
