Metadata-Version: 2.3
Name: python-hatch-template-win
Version: 0.0.1
Summary: hatch template win
Project-URL: Documentation, https://github.com/0num4/python-hatch-template-win#readme
Project-URL: Issues, https://github.com/0num4/python-hatch-template-win/issues
Project-URL: Source, https://github.com/0num4/python-hatch-template-win
Author-email: 0num4 <r.oonuma@matsuri-tech.com>
License-Expression: MIT
License-File: LICENSE.txt
Classifier: Development Status :: 4 - Beta
Classifier: Programming Language :: Python
Classifier: Programming Language :: Python :: 3.12
Classifier: Programming Language :: Python :: Implementation :: CPython
Classifier: Programming Language :: Python :: Implementation :: PyPy
Requires-Python: >=3.12
